authentication/__init__.py
authentication/config.py
authentication/getaccesstoken.py
datapunt_processing-0.0.1a1.dist-info/DESCRIPTION.rst
datapunt_processing-0.0.1a1.dist-info/METADATA
datapunt_processing-0.0.1a1.dist-info/RECORD
datapunt_processing-0.0.1a1.dist-info/WHEEL
datapunt_processing-0.0.1a1.dist-info/entry_points.txt
datapunt_processing-0.0.1a1.dist-info/metadata.json
datapunt_processing-0.0.1a1.dist-info/top_level.txt
extract/__init__.py
extract/csv_dataframe.py
extract/download_bbga_by_variable__area_year.py
extract/download_from_api_brk.py
extract/download_from_api_kvk.py
extract/download_from_api_tellus.py
extract/download_from_api_with_authentication.py
extract/download_from_catalog.py
extract/download_from_objectstore.py
extract/download_from_wfs.py
helpers/__init__.py
helpers/connections.py
helpers/files.py
helpers/json_dict_handlers.py
helpers/logging.py
helpers/xml_handlers.py
load/__init__.py
load/load_file_to_ckan.py
load/load_file_to_objectstore.py
load/load_wfs_to_postgres.py
load/load_xls_to_postgres.py
transform/__init__.py
transform/enrichment/__init__.py
transform/enrichment/add_knmi_data.py
transform/enrichment/add_public_events.py
transform/enrichment/knmi_metadata.py
transform/geospatial/__init__.py
transform/geospatial/api_clean_BAG_address_NED.py
transform/geospatial/api_get_areacodes_from_latlon.py
transform/geospatial/api_get_nearest_address_from_latlon.py
transform/geospatial/csv_get_centroid_of_street.py
transform/geospatial/divide_bbox_amsterdam_in_quadrants.py
transform/geospatial/postgres_add_areas_from_coordinates.py
transform/geospatial/rd_to_wgs84.py
transform/preprocessing/__init__.py
transform/preprocessing/data_selection.py
transform/preprocessing/enrichment.py
transform/preprocessing/ml_helperfunctions.py
transform/preprocessing/ml_preprocessing.py
transform/preprocessing/utilities.py
