Metadata-Version: 2.0
Name: datapunt-processing
Version: 0.0.1a1
Summary: Datapunt generic ETL command line scripts and functions for shell scripting in Docker.
Home-page: https://github.com/Amsterdam/data-processing
Author: Amsterdam Datapunt
Author-email: datapunt@amsterdam.nl
License: Mozilla Public License Version 2.0
Platform: UNKNOWN
Classifier: Development Status :: 2 - Pre-Alpha
Classifier: License :: OSI Approved :: Mozilla Public License 2.0 (MPL 2.0)
Classifier: Programming Language :: Python
Classifier: Programming Language :: Python :: 3.6
Classifier: Intended Audience :: Developers
Classifier: Intended Audience :: Science/Research
Classifier: Natural Language :: English
Classifier: Topic :: Scientific/Engineering :: Information Analysis
Requires-Dist: requests (==2.18.4)
Requires-Dist: xlrd (==1.1.0)
Requires-Dist: python-swiftclient (==3.4.0)
Requires-Dist: python-keystoneclient
Requires-Dist: datapunt-config-loader
Requires-Dist: configparser (==3.5.0)
Requires-Dist: sqlalchemy (==1.2.2)
Requires-Dist: psycopg2 (==2.7.3.2)
Requires-Dist: pandas (==0.22.0)
Requires-Dist: scikit-learn (==0.19.1)
Requires-Dist: docutils
Requires-Dist: pprint (>=0.1)
Requires-Dist: pyproj (==1.9.5.1)
Requires-Dist: requests-cache (==0.4.13)
Requires-Dist: logger (==1.4)
Requires-Dist: IPython (==6.2.1)
Provides-Extra: dev
Requires-Dist: jupyter; extra == 'dev'
Provides-Extra: docs
Requires-Dist: Sphinx; extra == 'docs'
Requires-Dist: sphinx-autobuild; extra == 'docs'
Requires-Dist: sphinx-argparse; extra == 'docs'
Requires-Dist: sphinx-rtd-theme; extra == 'docs'
Provides-Extra: test
Requires-Dist: pytest; extra == 'test'
Requires-Dist: pytest-runner; extra == 'test'
Requires-Dist: pytest-cov; extra == 'test'
Requires-Dist: flake8; extra == 'test'
